AI_Robot_Tools/AI_Speak.py
AI_Robot_Tools/AI_Speech_Recognition.py
AI_Robot_Tools/AI_Tools.py
AI_Robot_Tools/__init__.py
AI_Robot_Tools-2.0.0.1.dist-info/LICENSE
AI_Robot_Tools-2.0.0.1.dist-info/METADATA
AI_Robot_Tools-2.0.0.1.dist-info/WHEEL
AI_Robot_Tools-2.0.0.1.dist-info/top_level.txt
AI_Robot_Tools-2.0.0.1.dist-info/zip-safe
AI_Robot_Tools-2.0.0.1.dist-info/RECORD
