Metadata-Version: 2.1
Name: AI-Robot-Tools
Version: 2.0.0.1
Summary: AI_Robot_Tools
Home-page: UNKNOWN
Author: Rishabh
Author-email: rinku87096@gmail.com
License: UNKNOWN
Keywords: Speak,Speech,Speak and Speech Tools,AI Robot Tools,AI Jarvis,python tutorial,Rishabh
Platform: any
Classifier: Development Status :: 1 - Planning
Classifier: Intended Audience :: Developers
Classifier: Topic :: Software Development :: Libraries :: Python Modules
Classifier: Programming Language :: Python :: 3
Classifier: Operating System :: Unix
Classifier: Operating System :: MacOS :: MacOS X
Classifier: Operating System :: Microsoft :: Windows
License-File: LICENSE
Requires-Dist: pyttsx3
Requires-Dist: SpeechRecognition
Requires-Dist: googletrans
Requires-Dist: gTTS
